README.rst
pyproject.toml
setup.py
python/SQImFil/__init__.py
python/SQImFil/_exec_functions.py
python/SQImFil/_history.py
python/SQImFil/_imfil.py
python/SQImFil/_linalg.py
python/SQImFil/_optset.py
python/SQImFil/_util.py
python/SQImFil/_version.py
python/SQImFil.egg-info/PKG-INFO
python/SQImFil.egg-info/SOURCES.txt
python/SQImFil.egg-info/dependency_links.txt
python/SQImFil.egg-info/requires.txt
python/SQImFil.egg-info/top_level.txt
test/test_imfil.py